{
  "runId": 149,
  "totalInitialUtility": 6784.73424703007,
  "totalOptimizedUtility": 13117.754011266577,
  "utilityIncrease": 0.9334219342502185,
  "participationInPercent": 0.65,
  "auBalances": {
    "balanceBefore": {
      "NeuAU1": 15174.385239251318,
      "NeuAU2": 32825.61476074862
    },
    "balanceAfter": {
      "NeuAU1": 17282.267887027487,
      "NeuAU2": 30917.732112972448
    }
  },
  "initialFlightList": [
    {
      "departureTime": "07:30:00",
      "au": "NeuAU1",
      "flightId": 1
    },
    {
      "departureTime": "07:39:00",
      "au": "NeuAU1",
      "flightId": 14
    },
    {
      "departureTime": "07:58:00",
      "au": "NeuAU2",
      "flightId": 25
    },
    {
      "departureTime": "08:12:00",
      "au": "NeuAU2",
      "flightId": 30
    },
    {
      "departureTime": "08:19:00",
      "au": "NeuAU1",
      "flightId": 12
    },
    {
      "departureTime": "08:54:00",
      "au": "NeuAU2",
      "flightId": 37
    },
    {
      "departureTime": "09:14:00",
      "au": "NeuAU1",
      "flightId": 18
    },
    {
      "departureTime": "09:19:00",
      "au": "NeuAU1",
      "flightId": 11
    },
    {
      "departureTime": "09:30:00",
      "au": "NeuAU2",
      "flightId": 28
    },
    {
      "departureTime": "09:35:00",
      "au": "NeuAU2",
      "flightId": 33
    },
    {
      "departureTime": "09:57:00",
      "au": "NeuAU1",
      "flightId": 4
    },
    {
      "departureTime": "09:59:00",
      "au": "NeuAU2",
      "flightId": 22
    },
    {
      "departureTime": "10:05:00",
      "au": "NeuAU1",
      "flightId": 16
    },
    {
      "departureTime": "10:12:00",
      "au": "NeuAU1",
      "flightId": 13
    },
    {
      "departureTime": "10:16:00",
      "au": "NeuAU1",
      "flightId": 17
    },
    {
      "departureTime": "10:19:00",
      "au": "NeuAU2",
      "flightId": 20
    },
    {
      "departureTime": "11:21:00",
      "au": "NeuAU1",
      "flightId": 3
    },
    {
      "departureTime": "11:23:00",
      "au": "NeuAU2",
      "flightId": 36
    },
    {
      "departureTime": "11:51:00",
      "au": "NeuAU2",
      "flightId": 39
    },
    {
      "departureTime": "12:00:00",
      "au": "NeuAU2",
      "flightId": 23
    },
    {
      "departureTime": "12:01:00",
      "au": "NeuAU1",
      "flightId": 8
    },
    {
      "departureTime": "12:22:00",
      "au": "NeuAU1",
      "flightId": 6
    },
    {
      "departureTime": "12:28:00",
      "au": "NeuAU2",
      "flightId": 21
    },
    {
      "departureTime": "13:24:00",
      "au": "NeuAU1",
      "flightId": 5
    },
    {
      "departureTime": "14:04:00",
      "au": "NeuAU1",
      "flightId": 15
    },
    {
      "departureTime": "14:42:00",
      "au": "NeuAU2",
      "flightId": 24
    },
    {
      "departureTime": "15:32:00",
      "au": "NeuAU2",
      "flightId": 35
    },
    {
      "departureTime": "16:02:00",
      "au": "NeuAU2",
      "flightId": 38
    },
    {
      "departureTime": "16:04:00",
      "au": "NeuAU1",
      "flightId": 9
    },
    {
      "departureTime": "16:14:00",
      "au": "NeuAU2",
      "flightId": 32
    },
    {
      "departureTime": "16:18:00",
      "au": "NeuAU2",
      "flightId": 34
    },
    {
      "departureTime": "16:43:00",
      "au": "NeuAU1",
      "flightId": 19
    },
    {
      "departureTime": "17:50:00",
      "au": "NeuAU1",
      "flightId": 10
    },
    {
      "departureTime": "18:42:00",
      "au": "NeuAU1",
      "flightId": 2
    },
    {
      "departureTime": "19:04:00",
      "au": "NeuAU2",
      "flightId": 27
    },
    {
      "departureTime": "19:31:00",
      "au": "NeuAU2",
      "flightId": 26
    },
    {
      "departureTime": "19:41:00",
      "au": "NeuAU1",
      "flightId": 7
    },
    {
      "departureTime": "19:59:00",
      "au": "NeuAU1",
      "flightId": 0
    },
    {
      "departureTime": "20:05:00",
      "au": "NeuAU2",
      "flightId": 31
    },
    {
      "departureTime": "20:30:00",
      "au": "NeuAU2",
      "flightId": 29
    }
  ],
  "optimizedFlightList": [
    {
      "departureTime": "07:30:00",
      "au": "NeuAU1",
      "flightId": 1,
      "initialUtility": 1008.719261962566,
      "optimizedUtility": 1008.719261962566,
      "cost": 941.5606846165513,
      "optimized": true
    },
    {
      "departureTime": "07:39:00",
      "au": "NeuAU1",
      "flightId": 14,
      "initialUtility": 530.613967936473,
      "optimizedUtility": 530.613967936473,
      "cost": 495.28671629144606,
      "optimized": true
    },
    {
      "departureTime": "07:58:00",
      "au": "NeuAU1",
      "flightId": 12,
      "initialUtility": 1403.4354949044389,
      "optimizedUtility": 2017.438523925132,
      "cost": 695.9944452284212,
      "optimized": true
    },
    {
      "departureTime": "08:12:00",
      "au": "NeuAU2",
      "flightId": 30,
      "initialUtility": 1.0,
      "optimizedUtility": 1.0,
      "cost": 0.9334219342502186,
      "optimized": true
    },
    {
      "departureTime": "08:19:00",
      "au": "NeuAU2",
      "flightId": 25,
      "initialUtility": 1.0,
      "optimizedUtility": 567.3842214112306,
      "cost": -565.4507994769804,
      "optimized": true
    },
    {
      "departureTime": "08:54:00",
      "au": "NeuAU2",
      "flightId": 37,
      "initialUtility": 1.0,
      "optimizedUtility": 1.0,
      "cost": 0.9334219342502186,
      "optimized": true
    },
    {
      "departureTime": "09:14:00",
      "au": "NeuAU1",
      "flightId": 18,
      "initialUtility": 0.0,
      "optimizedUtility": 0.0,
      "cost": 0.0,
      "optimized": false
    },
    {
      "departureTime": "09:19:00",
      "au": "NeuAU2",
      "flightId": 28,
      "initialUtility": 1.0,
      "optimizedUtility": 1.0,
      "cost": 0.9334219342502186,
      "optimized": true
    },
    {
      "departureTime": "09:30:00",
      "au": "NeuAU2",
      "flightId": 22,
      "initialUtility": 1.0,
      "optimizedUtility": 1.0,
      "cost": 0.9334219342502186,
      "optimized": true
    },
    {
      "departureTime": "09:35:00",
      "au": "NeuAU1",
      "flightId": 16,
      "initialUtility": 1.0,
      "optimizedUtility": 1.0,
      "cost": 0.9334219342502186,
      "optimized": true
    },
    {
      "departureTime": "09:57:00",
      "au": "NeuAU1",
      "flightId": 4,
      "initialUtility": 0.0,
      "optimizedUtility": 0.0,
      "cost": 0.0,
      "optimized": false
    },
    {
      "departureTime": "09:59:00",
      "au": "NeuAU2",
      "flightId": 20,
      "initialUtility": 896.6071646992278,
      "optimizedUtility": 1456.9866426362444,
      "cost": 276.53331599914077,
      "optimized": true
    },
    {
      "departureTime": "10:05:00",
      "au": "NeuAU1",
      "flightId": 11,
      "initialUtility": 1.0,
      "optimizedUtility": 1344.9590159500863,
      "cost": -1343.025594015836,
      "optimized": true
    },
    {
      "departureTime": "10:12:00",
      "au": "NeuAU1",
      "flightId": 17,
      "initialUtility": 1.0,
      "optimizedUtility": 1.0,
      "cost": 0.9334219342502186,
      "optimized": true
    },
    {
      "departureTime": "10:16:00",
      "au": "NeuAU1",
      "flightId": 13,
      "initialUtility": 1.0,
      "optimizedUtility": 1.0,
      "cost": 0.9334219342502186,
      "optimized": true
    },
    {
      "departureTime": "10:19:00",
      "au": "NeuAU2",
      "flightId": 33,
      "initialUtility": 1.0,
      "optimizedUtility": 1741.179092161445,
      "cost": -1739.2456702271948,
      "optimized": true
    },
    {
      "departureTime": "11:21:00",
      "au": "NeuAU1",
      "flightId": 3,
      "initialUtility": 1.0,
      "optimizedUtility": 1.0,
      "cost": 0.9334219342502186,
      "optimized": true
    },
    {
      "departureTime": "11:23:00",
      "au": "NeuAU2",
      "flightId": 36,
      "initialUtility": 1.0,
      "optimizedUtility": 1.0,
      "cost": 0.9334219342502186,
      "optimized": true
    },
    {
      "departureTime": "11:51:00",
      "au": "NeuAU1",
      "flightId": 8,
      "initialUtility": 1.0,
      "optimizedUtility": 1.0,
      "cost": 0.9334219342502186,
      "optimized": true
    },
    {
      "departureTime": "12:00:00",
      "au": "NeuAU2",
      "flightId": 23,
      "initialUtility": 0.0,
      "optimizedUtility": 0.0,
      "cost": 0.0,
      "optimized": false
    },
    {
      "departureTime": "12:01:00",
      "au": "NeuAU1",
      "flightId": 6,
      "initialUtility": 1.0,
      "optimizedUtility": 1.0,
      "cost": 0.9334219342502186,
      "optimized": true
    },
    {
      "departureTime": "12:22:00",
      "au": "NeuAU2",
      "flightId": 39,
      "initialUtility": 1.0,
      "optimizedUtility": 1134.7684428224584,
      "cost": -1132.8350208882082,
      "optimized": true
    },
    {
      "departureTime": "12:28:00",
      "au": "NeuAU2",
      "flightId": 21,
      "initialUtility": 0.0,
      "optimizedUtility": 0.0,
      "cost": 0.0,
      "optimized": false
    },
    {
      "departureTime": "13:24:00",
      "au": "NeuAU1",
      "flightId": 5,
      "initialUtility": 201.74385239251322,
      "optimizedUtility": 201.74385239251322,
      "cost": 188.31213692331025,
      "optimized": true
    },
    {
      "departureTime": "14:04:00",
      "au": "NeuAU1",
      "flightId": 15,
      "initialUtility": 403.48770478502644,
      "optimizedUtility": 403.48770478502644,
      "cost": 376.6242738466205,
      "optimized": true
    },
    {
      "departureTime": "14:42:00",
      "au": "NeuAU2",
      "flightId": 24,
      "initialUtility": 1.0,
      "optimizedUtility": 1.0,
      "cost": 0.9334219342502186,
      "optimized": true
    },
    {
      "departureTime": "15:32:00",
      "au": "NeuAU2",
      "flightId": 38,
      "initialUtility": 756.5122952149725,
      "optimizedUtility": -2.6876715793909955E-12,
      "cost": 1462.6574650986072,
      "optimized": true
    },
    {
      "departureTime": "16:02:00",
      "au": "NeuAU2",
      "flightId": 32,
      "initialUtility": 872.8988021711228,
      "optimizedUtility": 1134.7684428224584,
      "cost": 552.9132476759328,
      "optimized": true
    },
    {
      "departureTime": "16:04:00",
      "au": "NeuAU1",
      "flightId": 9,
      "initialUtility": 0.0,
      "optimizedUtility": 0.0,
      "cost": 0.0,
      "optimized": false
    },
    {
      "departureTime": "16:14:00",
      "au": "NeuAU2",
      "flightId": 35,
      "initialUtility": 1.0,
      "optimizedUtility": 869.9891394972171,
      "cost": -868.055717562967,
      "optimized": true
    },
    {
      "departureTime": "16:18:00",
      "au": "NeuAU2",
      "flightId": 34,
      "initialUtility": 0.0,
      "optimizedUtility": 0.0,
      "cost": 0.0,
      "optimized": false
    },
    {
      "departureTime": "16:43:00",
      "au": "NeuAU1",
      "flightId": 19,
      "initialUtility": 693.7157029637292,
      "optimizedUtility": 693.7157029637292,
      "cost": 647.529453280154,
      "optimized": true
    },
    {
      "departureTime": "17:50:00",
      "au": "NeuAU1",
      "flightId": 10,
      "initialUtility": 0.0,
      "optimizedUtility": 0.0,
      "cost": 0.0,
      "optimized": false
    },
    {
      "departureTime": "18:42:00",
      "au": "NeuAU1",
      "flightId": 2,
      "initialUtility": 0.0,
      "optimizedUtility": 0.0,
      "cost": 0.0,
      "optimized": false
    },
    {
      "departureTime": "19:04:00",
      "au": "NeuAU2",
      "flightId": 27,
      "initialUtility": 0.0,
      "optimizedUtility": 0.0,
      "cost": 0.0,
      "optimized": false
    },
    {
      "departureTime": "19:31:00",
      "au": "NeuAU2",
      "flightId": 26,
      "initialUtility": 0.0,
      "optimizedUtility": 0.0,
      "cost": 0.0,
      "optimized": false
    },
    {
      "departureTime": "19:41:00",
      "au": "NeuAU1",
      "flightId": 7,
      "initialUtility": 0.0,
      "optimizedUtility": 0.0,
      "cost": 0.0,
      "optimized": false
    },
    {
      "departureTime": "19:59:00",
      "au": "NeuAU1",
      "flightId": 0,
      "initialUtility": 0.0,
      "optimizedUtility": 0.0,
      "cost": 0.0,
      "optimized": false
    },
    {
      "departureTime": "20:05:00",
      "au": "NeuAU2",
      "flightId": 31,
      "initialUtility": 0.0,
      "optimizedUtility": 0.0,
      "cost": 0.0,
      "optimized": false
    },
    {
      "departureTime": "20:30:00",
      "au": "NeuAU2",
      "flightId": 29,
      "initialUtility": 0.0,
      "optimizedUtility": 0.0,
      "cost": 0.0,
      "optimized": false
    }
  ]
}