{
  "runId": 132,
  "totalInitialUtility": 11305.994653460191,
  "totalOptimizedUtility": 24884.086852344615,
  "utilityIncrease": 1.20096396779463,
  "participationInPercent": 0.6306306306306306,
  "auBalances": {
    "balanceBefore": {
      "NeuAU1": 1430.4198812657237,
      "PasAU2": 76071.62851050337,
      "PasAU1": 51240.89945854921,
      "AggAU1": 233.09622166923054,
      "AggAU2": 2162.0656556968297,
      "NeuAU2": 361.89027231501666
    },
    "balanceAfter": {
      "NeuAU1": 2297.933680037922,
      "PasAU2": 77865.3236114519,
      "PasAU1": 49176.883999119535,
      "AggAU1": 333.09622166923054,
      "AggAU2": 1964.872215405847,
      "NeuAU2": 461.89027231501666
    }
  },
  "initialFlightList": [
    {
      "departureTime": "07:30:00",
      "au": "AggAU1",
      "flightId": 8
    },
    {
      "departureTime": "07:33:00",
      "au": "PasAU1",
      "flightId": 34
    },
    {
      "departureTime": "07:34:00",
      "au": "AggAU2",
      "flightId": 79
    },
    {
      "departureTime": "07:35:00",
      "au": "PasAU1",
      "flightId": 23
    },
    {
      "departureTime": "07:36:00",
      "au": "AggAU2",
      "flightId": 68
    },
    {
      "departureTime": "07:43:00",
      "au": "AggAU1",
      "flightId": 19
    },
    {
      "departureTime": "07:46:00",
      "au": "NeuAU1",
      "flightId": 56
    },
    {
      "departureTime": "07:47:00",
      "au": "NeuAU2",
      "flightId": 114
    },
    {
      "departureTime": "07:48:00",
      "au": "PasAU2",
      "flightId": 97
    },
    {
      "departureTime": "07:49:00",
      "au": "AggAU2",
      "flightId": 75
    },
    {
      "departureTime": "07:56:00",
      "au": "PasAU1",
      "flightId": 21
    },
    {
      "departureTime": "08:01:00",
      "au": "AggAU1",
      "flightId": 14
    },
    {
      "departureTime": "08:03:00",
      "au": "AggAU1",
      "flightId": 3
    },
    {
      "departureTime": "08:07:00",
      "au": "PasAU1",
      "flightId": 36
    },
    {
      "departureTime": "08:22:00",
      "au": "NeuAU2",
      "flightId": 106
    },
    {
      "departureTime": "08:24:00",
      "au": "NeuAU1",
      "flightId": 49
    },
    {
      "departureTime": "08:44:00",
      "au": "AggAU1",
      "flightId": 12
    },
    {
      "departureTime": "08:48:00",
      "au": "NeuAU2",
      "flightId": 102
    },
    {
      "departureTime": "08:51:00",
      "au": "PasAU1",
      "flightId": 32
    },
    {
      "departureTime": "09:00:00",
      "au": "AggAU1",
      "flightId": 11
    },
    {
      "departureTime": "09:10:00",
      "au": "AggAU1",
      "flightId": 18
    },
    {
      "departureTime": "09:18:00",
      "au": "NeuAU1",
      "flightId": 55
    },
    {
      "departureTime": "09:20:00",
      "au": "AggAU1",
      "flightId": 9
    },
    {
      "departureTime": "09:28:00",
      "au": "NeuAU1",
      "flightId": 51
    },
    {
      "departureTime": "09:30:00",
      "au": "AggAU1",
      "flightId": 4
    },
    {
      "departureTime": "09:38:00",
      "au": "NeuAU1",
      "flightId": 50
    },
    {
      "departureTime": "09:39:00",
      "au": "PasAU1",
      "flightId": 39
    },
    {
      "departureTime": "09:41:00",
      "au": "PasAU1",
      "flightId": 20
    },
    {
      "departureTime": "09:56:00",
      "au": "NeuAU1",
      "flightId": 41
    },
    {
      "departureTime": "10:02:00",
      "au": "NeuAU1",
      "flightId": 46
    },
    {
      "departureTime": "10:07:00",
      "au": "PasAU2",
      "flightId": 96
    },
    {
      "departureTime": "10:09:00",
      "au": "NeuAU2",
      "flightId": 104
    },
    {
      "departureTime": "10:23:00",
      "au": "PasAU2",
      "flightId": 90
    },
    {
      "departureTime": "10:26:00",
      "au": "NeuAU2",
      "flightId": 118
    },
    {
      "departureTime": "10:29:00",
      "au": "NeuAU1",
      "flightId": 59
    },
    {
      "departureTime": "10:30:00",
      "au": "AggAU1",
      "flightId": 5
    },
    {
      "departureTime": "10:33:00",
      "au": "PasAU2",
      "flightId": 86
    },
    {
      "departureTime": "10:40:00",
      "au": "AggAU2",
      "flightId": 61
    },
    {
      "departureTime": "10:42:00",
      "au": "PasAU1",
      "flightId": 26
    },
    {
      "departureTime": "10:43:00",
      "au": "NeuAU2",
      "flightId": 101
    },
    {
      "departureTime": "10:45:00",
      "au": "PasAU1",
      "flightId": 37
    },
    {
      "departureTime": "10:48:00",
      "au": "NeuAU2",
      "flightId": 112
    },
    {
      "departureTime": "10:49:00",
      "au": "NeuAU1",
      "flightId": 48
    },
    {
      "departureTime": "10:50:00",
      "au": "PasAU2",
      "flightId": 89
    },
    {
      "departureTime": "10:55:00",
      "au": "PasAU2",
      "flightId": 98
    },
    {
      "departureTime": "11:03:00",
      "au": "AggAU1",
      "flightId": 16
    },
    {
      "departureTime": "11:08:00",
      "au": "PasAU1",
      "flightId": 30
    },
    {
      "departureTime": "11:10:00",
      "au": "AggAU1",
      "flightId": 13
    },
    {
      "departureTime": "11:14:00",
      "au": "PasAU2",
      "flightId": 95
    },
    {
      "departureTime": "11:20:00",
      "au": "PasAU2",
      "flightId": 91
    },
    {
      "departureTime": "11:23:00",
      "au": "AggAU1",
      "flightId": 17
    },
    {
      "departureTime": "11:34:00",
      "au": "NeuAU2",
      "flightId": 100
    },
    {
      "departureTime": "11:51:00",
      "au": "PasAU2",
      "flightId": 88
    },
    {
      "departureTime": "11:52:00",
      "au": "PasAU2",
      "flightId": 94
    },
    {
      "departureTime": "11:55:00",
      "au": "PasAU1",
      "flightId": 28
    },
    {
      "departureTime": "11:58:00",
      "au": "AggAU2",
      "flightId": 73
    },
    {
      "departureTime": "12:02:00",
      "au": "PasAU2",
      "flightId": 81
    },
    {
      "departureTime": "12:03:00",
      "au": "NeuAU2",
      "flightId": 113
    },
    {
      "departureTime": "12:07:00",
      "au": "NeuAU2",
      "flightId": 109
    },
    {
      "departureTime": "12:10:00",
      "au": "PasAU2",
      "flightId": 85
    },
    {
      "departureTime": "12:11:00",
      "au": "AggAU2",
      "flightId": 70
    },
    {
      "departureTime": "12:14:00",
      "au": "AggAU2",
      "flightId": 63
    },
    {
      "departureTime": "12:18:00",
      "au": "PasAU2",
      "flightId": 83
    },
    {
      "departureTime": "12:22:00",
      "au": "NeuAU1",
      "flightId": 44
    },
    {
      "departureTime": "12:38:00",
      "au": "PasAU2",
      "flightId": 82
    },
    {
      "departureTime": "12:48:00",
      "au": "PasAU2",
      "flightId": 99
    },
    {
      "departureTime": "12:51:00",
      "au": "AggAU2",
      "flightId": 72
    },
    {
      "departureTime": "12:52:00",
      "au": "NeuAU2",
      "flightId": 108
    },
    {
      "departureTime": "12:53:00",
      "au": "AggAU2",
      "flightId": 69
    },
    {
      "departureTime": "12:58:00",
      "au": "AggAU2",
      "flightId": 77
    },
    {
      "departureTime": "13:01:00",
      "au": "AggAU2",
      "flightId": 65
    },
    {
      "departureTime": "13:04:00",
      "au": "NeuAU2",
      "flightId": 103
    },
    {
      "departureTime": "13:23:00",
      "au": "AggAU1",
      "flightId": 6
    },
    {
      "departureTime": "13:27:00",
      "au": "AggAU1",
      "flightId": 7
    },
    {
      "departureTime": "13:39:00",
      "au": "NeuAU1",
      "flightId": 45
    },
    {
      "departureTime": "13:42:00",
      "au": "PasAU1",
      "flightId": 24
    },
    {
      "departureTime": "13:46:00",
      "au": "PasAU1",
      "flightId": 31
    },
    {
      "departureTime": "13:51:00",
      "au": "NeuAU1",
      "flightId": 58
    },
    {
      "departureTime": "14:03:00",
      "au": "AggAU2",
      "flightId": 71
    },
    {
      "departureTime": "14:07:00",
      "au": "NeuAU1",
      "flightId": 57
    },
    {
      "departureTime": "14:13:00",
      "au": "NeuAU1",
      "flightId": 40
    },
    {
      "departureTime": "14:27:00",
      "au": "NeuAU2",
      "flightId": 105
    },
    {
      "departureTime": "14:41:00",
      "au": "NeuAU2",
      "flightId": 119
    },
    {
      "departureTime": "14:44:00",
      "au": "AggAU2",
      "flightId": 66
    },
    {
      "departureTime": "14:45:00",
      "au": "NeuAU2",
      "flightId": 111
    },
    {
      "departureTime": "14:47:00",
      "au": "AggAU1",
      "flightId": 2
    },
    {
      "departureTime": "14:57:00",
      "au": "NeuAU1",
      "flightId": 53
    },
    {
      "departureTime": "15:24:00",
      "au": "PasAU1",
      "flightId": 33
    },
    {
      "departureTime": "15:28:00",
      "au": "AggAU2",
      "flightId": 62
    },
    {
      "departureTime": "15:30:00",
      "au": "PasAU1",
      "flightId": 29
    },
    {
      "departureTime": "15:33:00",
      "au": "NeuAU1",
      "flightId": 43
    },
    {
      "departureTime": "15:47:00",
      "au": "PasAU1",
      "flightId": 25
    },
    {
      "departureTime": "15:54:00",
      "au": "NeuAU1",
      "flightId": 47
    },
    {
      "departureTime": "15:56:00",
      "au": "AggAU2",
      "flightId": 74
    },
    {
      "departureTime": "15:59:00",
      "au": "AggAU2",
      "flightId": 76
    },
    {
      "departureTime": "16:13:00",
      "au": "PasAU1",
      "flightId": 22
    },
    {
      "departureTime": "16:14:00",
      "au": "NeuAU2",
      "flightId": 117
    },
    {
      "departureTime": "16:35:00",
      "au": "NeuAU1",
      "flightId": 52
    },
    {
      "departureTime": "16:39:00",
      "au": "NeuAU1",
      "flightId": 42
    },
    {
      "departureTime": "16:46:00",
      "au": "PasAU2",
      "flightId": 80
    },
    {
      "departureTime": "17:01:00",
      "au": "PasAU2",
      "flightId": 87
    },
    {
      "departureTime": "17:04:00",
      "au": "AggAU1",
      "flightId": 15
    },
    {
      "departureTime": "17:15:00",
      "au": "PasAU1",
      "flightId": 38
    },
    {
      "departureTime": "17:17:00",
      "au": "AggAU2",
      "flightId": 64
    },
    {
      "departureTime": "17:20:00",
      "au": "AggAU2",
      "flightId": 67
    },
    {
      "departureTime": "17:31:00",
      "au": "AggAU2",
      "flightId": 60
    },
    {
      "departureTime": "17:47:00",
      "au": "NeuAU2",
      "flightId": 116
    },
    {
      "departureTime": "17:55:00",
      "au": "PasAU2",
      "flightId": 92
    },
    {
      "departureTime": "17:59:00",
      "au": "PasAU2",
      "flightId": 84
    },
    {
      "departureTime": "18:00:00",
      "au": "AggAU2",
      "flightId": 78
    },
    {
      "departureTime": "18:02:00",
      "au": "PasAU2",
      "flightId": 93
    },
    {
      "departureTime": "18:17:00",
      "au": "AggAU1",
      "flightId": 1
    },
    {
      "departureTime": "18:34:00",
      "au": "AggAU1",
      "flightId": 10
    },
    {
      "departureTime": "18:46:00",
      "au": "NeuAU2",
      "flightId": 107
    },
    {
      "departureTime": "18:53:00",
      "au": "PasAU1",
      "flightId": 35
    },
    {
      "departureTime": "18:54:00",
      "au": "NeuAU1",
      "flightId": 54
    },
    {
      "departureTime": "19:15:00",
      "au": "NeuAU2",
      "flightId": 110
    },
    {
      "departureTime": "19:23:00",
      "au": "PasAU1",
      "flightId": 27
    },
    {
      "departureTime": "19:25:00",
      "au": "NeuAU2",
      "flightId": 115
    },
    {
      "departureTime": "20:30:00",
      "au": "AggAU1",
      "flightId": 0
    }
  ],
  "optimizedFlightList": [
    {
      "departureTime": "07:30:00",
      "au": "AggAU1",
      "flightId": 8,
      "initialUtility": 1218.8839403697516,
      "optimizedUtility": 1131.8208017719103,
      "cost": 3435.722036323837,
      "optimized": false
    },
    {
      "departureTime": "07:33:00",
      "au": "AggAU2",
      "flightId": 68,
      "initialUtility": 864.7058823529399,
      "optimizedUtility": 957.3529411764689,
      "cost": 945.8335486224141,
      "optimized": true
    },
    {
      "departureTime": "07:34:00",
      "au": "NeuAU1",
      "flightId": 56,
      "initialUtility": 719.4033695687604,
      "optimizedUtility": 888.6747506437624,
      "cost": 694.7061440871229,
      "optimized": true
    },
    {
      "departureTime": "07:35:00",
      "au": "PasAU1",
      "flightId": 23,
      "initialUtility": 1.0,
      "optimizedUtility": 1.0,
      "cost": 1.20096396779463,
      "optimized": true
    },
    {
      "departureTime": "07:36:00",
      "au": "AggAU2",
      "flightId": 75,
      "initialUtility": 1.0,
      "optimizedUtility": 1.0,
      "cost": 1.20096396779463,
      "optimized": true
    },
    {
      "departureTime": "07:43:00",
      "au": "AggAU1",
      "flightId": 19,
      "initialUtility": 1.0,
      "optimizedUtility": 438.79821853311154,
      "cost": -435.0509029054151,
      "optimized": false
    },
    {
      "departureTime": "07:46:00",
      "au": "PasAU2",
      "flightId": 97,
      "initialUtility": 1.0,
      "optimizedUtility": 1.0,
      "cost": 1.20096396779463,
      "optimized": true
    },
    {
      "departureTime": "07:47:00",
      "au": "NeuAU2",
      "flightId": 114,
      "initialUtility": 1.0,
      "optimizedUtility": 1.0,
      "cost": 2.747315627696408,
      "optimized": false
    },
    {
      "departureTime": "07:48:00",
      "au": "PasAU1",
      "flightId": 34,
      "initialUtility": 1.0,
      "optimizedUtility": 1.0,
      "cost": 1.20096396779463,
      "optimized": true
    },
    {
      "departureTime": "07:49:00",
      "au": "PasAU1",
      "flightId": 21,
      "initialUtility": 1.0,
      "optimizedUtility": 1.0,
      "cost": 1.20096396779463,
      "optimized": true
    },
    {
      "departureTime": "07:56:00",
      "au": "NeuAU1",
      "flightId": 49,
      "initialUtility": 1.0,
      "optimizedUtility": 1.0,
      "cost": 1.20096396779463,
      "optimized": true
    },
    {
      "departureTime": "08:01:00",
      "au": "AggAU1",
      "flightId": 14,
      "initialUtility": 36.93587698090131,
      "optimizedUtility": 229.00243728158972,
      "cost": -90.59204824838622,
      "optimized": false
    },
    {
      "departureTime": "08:03:00",
      "au": "AggAU1",
      "flightId": 3,
      "initialUtility": 1.0,
      "optimizedUtility": 1.0,
      "cost": 2.747315627696408,
      "optimized": false
    },
    {
      "departureTime": "08:07:00",
      "au": "AggAU2",
      "flightId": 79,
      "initialUtility": 1.0,
      "optimizedUtility": 940.9090909090913,
      "cost": -938.7081269412967,
      "optimized": true
    },
    {
      "departureTime": "08:22:00",
      "au": "NeuAU2",
      "flightId": 106,
      "initialUtility": 1.0,
      "optimizedUtility": 1.0,
      "cost": 2.747315627696408,
      "optimized": false
    },
    {
      "departureTime": "08:24:00",
      "au": "PasAU1",
      "flightId": 32,
      "initialUtility": 321.8639393630416,
      "optimizedUtility": 440.90950597676925,
      "cost": 267.501427093721,
      "optimized": true
    },
    {
      "departureTime": "08:44:00",
      "au": "AggAU1",
      "flightId": 12,
      "initialUtility": 1.0,
      "optimizedUtility": 853.2187582588261,
      "cost": -849.4714426311298,
      "optimized": false
    },
    {
      "departureTime": "08:48:00",
      "au": "NeuAU2",
      "flightId": 102,
      "initialUtility": 1.0,
      "optimizedUtility": 1.0,
      "cost": 2.747315627696408,
      "optimized": false
    },
    {
      "departureTime": "08:51:00",
      "au": "NeuAU1",
      "flightId": 55,
      "initialUtility": 1.0,
      "optimizedUtility": 1.0,
      "cost": 1.20096396779463,
      "optimized": true
    },
    {
      "departureTime": "09:00:00",
      "au": "AggAU1",
      "flightId": 11,
      "initialUtility": 1.0,
      "optimizedUtility": 1116.241082233351,
      "cost": -1112.4937666056546,
      "optimized": false
    },
    {
      "departureTime": "09:10:00",
      "au": "AggAU1",
      "flightId": 18,
      "initialUtility": 77.5653416598929,
      "optimizedUtility": 365.66518211092546,
      "cost": -75.00336514119755,
      "optimized": false
    },
    {
      "departureTime": "09:18:00",
      "au": "NeuAU1",
      "flightId": 51,
      "initialUtility": 218.099664077407,
      "optimizedUtility": 308.9745241096604,
      "cost": 171.05497791282522,
      "optimized": true
    },
    {
      "departureTime": "09:20:00",
      "au": "AggAU1",
      "flightId": 9,
      "initialUtility": 1.0,
      "optimizedUtility": 780.085721836652,
      "cost": -776.3384062089557,
      "optimized": false
    },
    {
      "departureTime": "09:28:00",
      "au": "PasAU1",
      "flightId": 20,
      "initialUtility": 315.39344921039543,
      "optimizedUtility": 391.3215017980835,
      "cost": 302.84811559246253,
      "optimized": true
    },
    {
      "departureTime": "09:30:00",
      "au": "AggAU1",
      "flightId": 4,
      "initialUtility": 0.0,
      "optimizedUtility": 853.2187582588291,
      "cost": -853.2187582588291,
      "optimized": false
    },
    {
      "departureTime": "09:38:00",
      "au": "PasAU1",
      "flightId": 36,
      "initialUtility": 1.0,
      "optimizedUtility": 1406.840485224337,
      "cost": -1404.6395212565424,
      "optimized": true
    },
    {
      "departureTime": "09:39:00",
      "au": "NeuAU1",
      "flightId": 46,
      "initialUtility": 177.56396893574777,
      "optimizedUtility": 309.30497814614097,
      "cost": 81.50691946004486,
      "optimized": true
    },
    {
      "departureTime": "09:41:00",
      "au": "PasAU2",
      "flightId": 96,
      "initialUtility": 1.0,
      "optimizedUtility": 1.0,
      "cost": 1.20096396779463,
      "optimized": true
    },
    {
      "departureTime": "09:56:00",
      "au": "PasAU2",
      "flightId": 90,
      "initialUtility": 1.0,
      "optimizedUtility": 1.0,
      "cost": 1.20096396779463,
      "optimized": true
    },
    {
      "departureTime": "10:02:00",
      "au": "NeuAU1",
      "flightId": 59,
      "initialUtility": 86.63403323074789,
      "optimizedUtility": 157.51642405590505,
      "cost": 33.16196146969364,
      "optimized": true
    },
    {
      "departureTime": "10:07:00",
      "au": "PasAU2",
      "flightId": 86,
      "initialUtility": 1.0,
      "optimizedUtility": 1.0,
      "cost": 1.20096396779463,
      "optimized": true
    },
    {
      "departureTime": "10:09:00",
      "au": "NeuAU2",
      "flightId": 104,
      "initialUtility": 1.0,
      "optimizedUtility": 1085.7142857142862,
      "cost": -1081.9669700865898,
      "optimized": false
    },
    {
      "departureTime": "10:23:00",
      "au": "PasAU1",
      "flightId": 37,
      "initialUtility": 107.62714094612407,
      "optimizedUtility": 149.90923203210156,
      "cost": 86.97422714707159,
      "optimized": true
    },
    {
      "departureTime": "10:26:00",
      "au": "NeuAU2",
      "flightId": 118,
      "initialUtility": 1.0,
      "optimizedUtility": 369.230769230768,
      "cost": -365.48345360307155,
      "optimized": false
    },
    {
      "departureTime": "10:29:00",
      "au": "PasAU2",
      "flightId": 89,
      "initialUtility": 1.0,
      "optimizedUtility": 1.0,
      "cost": 1.20096396779463,
      "optimized": true
    },
    {
      "departureTime": "10:30:00",
      "au": "AggAU1",
      "flightId": 5,
      "initialUtility": 1.0,
      "optimizedUtility": 700.8582657126069,
      "cost": -697.1109500849105,
      "optimized": false
    },
    {
      "departureTime": "10:33:00",
      "au": "PasAU1",
      "flightId": 39,
      "initialUtility": 1.0,
      "optimizedUtility": 299.8184640642032,
      "cost": -297.6175000964086,
      "optimized": true
    },
    {
      "departureTime": "10:40:00",
      "au": "NeuAU1",
      "flightId": 48,
      "initialUtility": 1.0,
      "optimizedUtility": 1.0,
      "cost": 1.20096396779463,
      "optimized": true
    },
    {
      "departureTime": "10:42:00",
      "au": "PasAU1",
      "flightId": 30,
      "initialUtility": 1.0,
      "optimizedUtility": 1.0,
      "cost": 1.20096396779463,
      "optimized": true
    },
    {
      "departureTime": "10:43:00",
      "au": "NeuAU2",
      "flightId": 101,
      "initialUtility": 631.3432835820895,
      "optimizedUtility": 859.7014925373142,
      "cost": 1506.141060471015,
      "optimized": false
    },
    {
      "departureTime": "10:45:00",
      "au": "PasAU2",
      "flightId": 95,
      "initialUtility": 1.0,
      "optimizedUtility": 1.0,
      "cost": 1.20096396779463,
      "optimized": true
    },
    {
      "departureTime": "10:48:00",
      "au": "NeuAU2",
      "flightId": 112,
      "initialUtility": 1.0,
      "optimizedUtility": 1.0,
      "cost": 2.747315627696408,
      "optimized": false
    },
    {
      "departureTime": "10:49:00",
      "au": "PasAU2",
      "flightId": 98,
      "initialUtility": 1.0,
      "optimizedUtility": 1.0,
      "cost": 1.20096396779463,
      "optimized": true
    },
    {
      "departureTime": "10:50:00",
      "au": "PasAU1",
      "flightId": 26,
      "initialUtility": 1.0,
      "optimizedUtility": 1.0,
      "cost": 1.20096396779463,
      "optimized": true
    },
    {
      "departureTime": "10:55:00",
      "au": "PasAU2",
      "flightId": 91,
      "initialUtility": 1.0,
      "optimizedUtility": 1.0,
      "cost": 1.20096396779463,
      "optimized": true
    },
    {
      "departureTime": "11:03:00",
      "au": "AggAU1",
      "flightId": 16,
      "initialUtility": 251.6405554311743,
      "optimizedUtility": 975.1071522958013,
      "cost": -32.13056636635747,
      "optimized": false
    },
    {
      "departureTime": "11:08:00",
      "au": "NeuAU1",
      "flightId": 41,
      "initialUtility": 1.0,
      "optimizedUtility": 551.3074841956677,
      "cost": -549.106520227873,
      "optimized": true
    },
    {
      "departureTime": "11:10:00",
      "au": "AggAU1",
      "flightId": 13,
      "initialUtility": 1.0,
      "optimizedUtility": 921.9194894433028,
      "cost": -918.1721738156065,
      "optimized": false
    },
    {
      "departureTime": "11:14:00",
      "au": "NeuAU1",
      "flightId": 50,
      "initialUtility": 1.0,
      "optimizedUtility": 389.1582241381181,
      "cost": -386.9572601703235,
      "optimized": true
    },
    {
      "departureTime": "11:20:00",
      "au": "AggAU2",
      "flightId": 61,
      "initialUtility": 1.0,
      "optimizedUtility": 286.363636363637,
      "cost": -284.1626723958424,
      "optimized": true
    },
    {
      "departureTime": "11:23:00",
      "au": "AggAU1",
      "flightId": 17,
      "initialUtility": 1.0,
      "optimizedUtility": 853.2187582588261,
      "cost": -849.4714426311298,
      "optimized": false
    },
    {
      "departureTime": "11:34:00",
      "au": "NeuAU2",
      "flightId": 100,
      "initialUtility": 1.0,
      "optimizedUtility": 1.0,
      "cost": 2.747315627696408,
      "optimized": false
    },
    {
      "departureTime": "11:51:00",
      "au": "PasAU2",
      "flightId": 88,
      "initialUtility": 975.7500633563444,
      "optimizedUtility": 975.7500633563444,
      "cost": 1171.8406676642967,
      "optimized": true
    },
    {
      "departureTime": "11:52:00",
      "au": "AggAU2",
      "flightId": 70,
      "initialUtility": 0.0,
      "optimizedUtility": 142.50000000000045,
      "cost": -142.50000000000045,
      "optimized": true
    },
    {
      "departureTime": "11:55:00",
      "au": "PasAU2",
      "flightId": 83,
      "initialUtility": 328.53537486745535,
      "optimizedUtility": 433.48417517233725,
      "cost": 289.61034705683346,
      "optimized": true
    },
    {
      "departureTime": "11:58:00",
      "au": "PasAU1",
      "flightId": 28,
      "initialUtility": 234.23317505015893,
      "optimizedUtility": 224.8638480481526,
      "cost": 290.6749302993793,
      "optimized": true
    },
    {
      "departureTime": "12:02:00",
      "au": "PasAU2",
      "flightId": 94,
      "initialUtility": 1.0,
      "optimizedUtility": 1.0,
      "cost": 1.20096396779463,
      "optimized": true
    },
    {
      "departureTime": "12:03:00",
      "au": "NeuAU2",
      "flightId": 113,
      "initialUtility": 1.0,
      "optimizedUtility": 1.0,
      "cost": 2.747315627696408,
      "optimized": false
    },
    {
      "departureTime": "12:07:00",
      "au": "NeuAU2",
      "flightId": 109,
      "initialUtility": 103.84615384615402,
      "optimizedUtility": 129.80769230769226,
      "cost": 259.3366228761662,
      "optimized": false
    },
    {
      "departureTime": "12:10:00",
      "au": "PasAU2",
      "flightId": 82,
      "initialUtility": 1.0,
      "optimizedUtility": 1.0,
      "cost": 1.20096396779463,
      "optimized": true
    },
    {
      "departureTime": "12:11:00",
      "au": "AggAU2",
      "flightId": 73,
      "initialUtility": 1.0,
      "optimizedUtility": 1.0,
      "cost": 1.20096396779463,
      "optimized": true
    },
    {
      "departureTime": "12:14:00",
      "au": "PasAU2",
      "flightId": 81,
      "initialUtility": 1.0,
      "optimizedUtility": 1.0,
      "cost": 1.20096396779463,
      "optimized": true
    },
    {
      "departureTime": "12:18:00",
      "au": "PasAU2",
      "flightId": 85,
      "initialUtility": 1.0,
      "optimizedUtility": 1.0,
      "cost": 1.20096396779463,
      "optimized": true
    },
    {
      "departureTime": "12:22:00",
      "au": "PasAU2",
      "flightId": 99,
      "initialUtility": 627.1160537911134,
      "optimizedUtility": 903.4722808855031,
      "cost": 476.7875571342963,
      "optimized": true
    },
    {
      "departureTime": "12:38:00",
      "au": "AggAU2",
      "flightId": 69,
      "initialUtility": 1.0,
      "optimizedUtility": 1.0,
      "cost": 1.20096396779463,
      "optimized": true
    },
    {
      "departureTime": "12:48:00",
      "au": "AggAU2",
      "flightId": 63,
      "initialUtility": 1.0,
      "optimizedUtility": 1376.4705882352946,
      "cost": -1374.2696242675,
      "optimized": true
    },
    {
      "departureTime": "12:51:00",
      "au": "AggAU2",
      "flightId": 77,
      "initialUtility": 1.0,
      "optimizedUtility": 1.0,
      "cost": 1.20096396779463,
      "optimized": true
    },
    {
      "departureTime": "12:52:00",
      "au": "NeuAU2",
      "flightId": 108,
      "initialUtility": 1.0,
      "optimizedUtility": 1090.90909090909,
      "cost": -1087.1617752813936,
      "optimized": false
    },
    {
      "departureTime": "12:53:00",
      "au": "AggAU2",
      "flightId": 72,
      "initialUtility": 1.0,
      "optimizedUtility": 1.0,
      "cost": 1.20096396779463,
      "optimized": true
    },
    {
      "departureTime": "12:58:00",
      "au": "NeuAU1",
      "flightId": 44,
      "initialUtility": 1.0,
      "optimizedUtility": 1296.1351465171617,
      "cost": -1293.934182549367,
      "optimized": true
    },
    {
      "departureTime": "13:04:00",
      "au": "NeuAU2",
      "flightId": 103,
      "initialUtility": 1.0,
      "optimizedUtility": 1.0,
      "cost": 2.747315627696408,
      "optimized": false
    },
    {
      "departureTime": "13:23:00",
      "au": "AggAU1",
      "flightId": 6,
      "initialUtility": 1.0,
      "optimizedUtility": 1.0,
      "cost": 2.747315627696408,
      "optimized": false
    },
    {
      "departureTime": "13:27:00",
      "au": "AggAU1",
      "flightId": 7,
      "initialUtility": 71.34930382652212,
      "optimizedUtility": 243.7767880739503,
      "cost": 23.591573180435176,
      "optimized": false
    },
    {
      "departureTime": "13:39:00",
      "au": "AggAU2",
      "flightId": 71,
      "initialUtility": 497.56097560975553,
      "optimizedUtility": 1200.0000000000002,
      "cost": -104.88622090218564,
      "optimized": true
    },
    {
      "departureTime": "13:42:00",
      "au": "NeuAU1",
      "flightId": 58,
      "initialUtility": 756.0788354683438,
      "optimizedUtility": 918.0957287829907,
      "cost": 746.0065448949584,
      "optimized": true
    },
    {
      "departureTime": "13:46:00",
      "au": "NeuAU1",
      "flightId": 45,
      "initialUtility": 604.9543822436924,
      "optimizedUtility": 525.0547468530162,
      "cost": 806.4280506248101,
      "optimized": true
    },
    {
      "departureTime": "13:51:00",
      "au": "PasAU1",
      "flightId": 31,
      "initialUtility": 115.08183469131009,
      "optimizedUtility": 107.51066135635551,
      "cost": 145.78031014691604,
      "optimized": true
    },
    {
      "departureTime": "14:03:00",
      "au": "PasAU1",
      "flightId": 24,
      "initialUtility": 1.0,
      "optimizedUtility": 1.0,
      "cost": 1.20096396779463,
      "optimized": true
    },
    {
      "departureTime": "14:07:00",
      "au": "NeuAU1",
      "flightId": 40,
      "initialUtility": 1.0,
      "optimizedUtility": 1.0,
      "cost": 1.20096396779463,
      "optimized": true
    },
    {
      "departureTime": "14:13:00",
      "au": "NeuAU1",
      "flightId": 57,
      "initialUtility": 1.0,
      "optimizedUtility": 1.0,
      "cost": 1.20096396779463,
      "optimized": true
    },
    {
      "departureTime": "14:27:00",
      "au": "NeuAU2",
      "flightId": 105,
      "initialUtility": 1.0,
      "optimizedUtility": 1.0,
      "cost": 2.747315627696408,
      "optimized": false
    },
    {
      "departureTime": "14:41:00",
      "au": "NeuAU2",
      "flightId": 119,
      "initialUtility": 1.0,
      "optimizedUtility": 1.0,
      "cost": 2.747315627696408,
      "optimized": false
    },
    {
      "departureTime": "14:44:00",
      "au": "AggAU2",
      "flightId": 66,
      "initialUtility": 920.4545454545449,
      "optimizedUtility": 920.4545454545449,
      "cost": 1105.432743083693,
      "optimized": true
    },
    {
      "departureTime": "14:45:00",
      "au": "NeuAU2",
      "flightId": 111,
      "initialUtility": 1.0,
      "optimizedUtility": 1467.3913043478278,
      "cost": -1463.6439887201313,
      "optimized": false
    },
    {
      "departureTime": "14:47:00",
      "au": "AggAU1",
      "flightId": 2,
      "initialUtility": 0.0,
      "optimizedUtility": 975.1071522958013,
      "cost": -975.1071522958013,
      "optimized": false
    },
    {
      "departureTime": "14:57:00",
      "au": "PasAU1",
      "flightId": 33,
      "initialUtility": 1.0,
      "optimizedUtility": 1.0,
      "cost": 1.20096396779463,
      "optimized": true
    },
    {
      "departureTime": "15:24:00",
      "au": "NeuAU1",
      "flightId": 43,
      "initialUtility": 925.4089913284391,
      "optimizedUtility": 1102.6149683913352,
      "cost": 934.1768769957328,
      "optimized": true
    },
    {
      "departureTime": "15:28:00",
      "au": "AggAU2",
      "flightId": 62,
      "initialUtility": 387.93103448275724,
      "optimizedUtility": 387.93103448275724,
      "cost": 465.89119440308764,
      "optimized": true
    },
    {
      "departureTime": "15:30:00",
      "au": "NeuAU1",
      "flightId": 47,
      "initialUtility": 1.0,
      "optimizedUtility": 1.0,
      "cost": 1.20096396779463,
      "optimized": true
    },
    {
      "departureTime": "15:33:00",
      "au": "AggAU2",
      "flightId": 76,
      "initialUtility": 1.0,
      "optimizedUtility": 1.0,
      "cost": 1.20096396779463,
      "optimized": true
    },
    {
      "departureTime": "15:47:00",
      "au": "NeuAU1",
      "flightId": 53,
      "initialUtility": 1.0,
      "optimizedUtility": 1130.8871470680367,
      "cost": -1128.686183100242,
      "optimized": true
    },
    {
      "departureTime": "15:54:00",
      "au": "PasAU1",
      "flightId": 22,
      "initialUtility": 1.0,
      "optimizedUtility": 1.0,
      "cost": 1.20096396779463,
      "optimized": true
    },
    {
      "departureTime": "15:59:00",
      "au": "PasAU1",
      "flightId": 29,
      "initialUtility": 1.0,
      "optimizedUtility": 381.5871360817142,
      "cost": -379.3861721139196,
      "optimized": true
    },
    {
      "departureTime": "16:13:00",
      "au": "NeuAU1",
      "flightId": 52,
      "initialUtility": 990.4114882419229,
      "optimizedUtility": 1417.6478165031451,
      "cost": 762.2121824071821,
      "optimized": true
    },
    {
      "departureTime": "16:14:00",
      "au": "NeuAU2",
      "flightId": 117,
      "initialUtility": 1.0,
      "optimizedUtility": 1049.9999999999998,
      "cost": -1046.2526843723033,
      "optimized": false
    },
    {
      "departureTime": "16:35:00",
      "au": "PasAU1",
      "flightId": 25,
      "initialUtility": 1.0,
      "optimizedUtility": 1187.9599519525032,
      "cost": -1185.7589879847085,
      "optimized": true
    },
    {
      "departureTime": "16:39:00",
      "au": "PasAU2",
      "flightId": 87,
      "initialUtility": 1.0,
      "optimizedUtility": 1.0,
      "cost": 1.20096396779463,
      "optimized": true
    },
    {
      "departureTime": "16:46:00",
      "au": "NeuAU1",
      "flightId": 42,
      "initialUtility": 0.0,
      "optimizedUtility": 110.26149683913395,
      "cost": -110.26149683913395,
      "optimized": true
    },
    {
      "departureTime": "17:01:00",
      "au": "AggAU2",
      "flightId": 67,
      "initialUtility": 243.75000000000003,
      "optimizedUtility": 600.0000000000001,
      "cost": -63.515032850059015,
      "optimized": true
    },
    {
      "departureTime": "17:04:00",
      "au": "AggAU1",
      "flightId": 15,
      "initialUtility": 1.0,
      "optimizedUtility": 731.3303642218509,
      "cost": -727.5830485941545,
      "optimized": false
    },
    {
      "departureTime": "17:15:00",
      "au": "PasAU1",
      "flightId": 38,
      "initialUtility": 1.0,
      "optimizedUtility": 474.3396595642615,
      "cost": -470.5923439365651,
      "optimized": false
    },
    {
      "departureTime": "17:17:00",
      "au": "AggAU2",
      "flightId": 64,
      "initialUtility": 1.0,
      "optimizedUtility": 849.9999999999985,
      "cost": -846.2526843723022,
      "optimized": false
    },
    {
      "departureTime": "17:20:00",
      "au": "AggAU2",
      "flightId": 60,
      "initialUtility": 243.7499999999995,
      "optimizedUtility": 450.000000000001,
      "cost": 86.48496714993894,
      "optimized": true
    },
    {
      "departureTime": "17:31:00",
      "au": "PasAU2",
      "flightId": 80,
      "initialUtility": 1.0,
      "optimizedUtility": 981.3578223411517,
      "cost": -979.1568583733571,
      "optimized": true
    },
    {
      "departureTime": "17:47:00",
      "au": "NeuAU2",
      "flightId": 116,
      "initialUtility": 1.0,
      "optimizedUtility": 1.0,
      "cost": 2.747315627696408,
      "optimized": false
    },
    {
      "departureTime": "17:55:00",
      "au": "PasAU2",
      "flightId": 92,
      "initialUtility": 1.0,
      "optimizedUtility": 93.5413220108728,
      "cost": -89.7940063831764,
      "optimized": false
    },
    {
      "departureTime": "17:59:00",
      "au": "PasAU2",
      "flightId": 84,
      "initialUtility": 598.6864511891898,
      "optimizedUtility": 598.6864511891898,
      "cost": 719.0008558850556,
      "optimized": true
    },
    {
      "departureTime": "18:00:00",
      "au": "AggAU2",
      "flightId": 78,
      "initialUtility": 1.0,
      "optimizedUtility": 449.99999999999994,
      "cost": -446.2526843723035,
      "optimized": false
    },
    {
      "departureTime": "18:17:00",
      "au": "AggAU1",
      "flightId": 1,
      "initialUtility": 1.0,
      "optimizedUtility": 975.1071522958013,
      "cost": -971.3598366681049,
      "optimized": false
    },
    {
      "departureTime": "18:34:00",
      "au": "AggAU1",
      "flightId": 10,
      "initialUtility": 362.7630774909973,
      "optimizedUtility": 609.4419701848758,
      "cost": 749.9457792483815,
      "optimized": false
    },
    {
      "departureTime": "18:46:00",
      "au": "NeuAU2",
      "flightId": 107,
      "initialUtility": 183.6734693877549,
      "optimizedUtility": 293.8775510204068,
      "cost": 394.40491120954493,
      "optimized": false
    }
  ]
}